demux1t4.v
`timescale 1ns / 1ps
//////////////////////////////////////////////////////////////////////////////////
// Company: 
// Engineer: 
// 
// Create Date: 10.04.2026 09:27:39
// Design Name: 
// Module Name: demux1t4
// Project Name: 
// Target Devices: 
// Tool Versions: 
// Description: 
// 
// Dependencies: 
// 
// Revision:
// Revision 0.01 - File Created
// Additional Comments:
// 
//////////////////////////////////////////////////////////////////////////////////


//1-bit 4:1 DeMux using 1-bit 2:1 Demux
module demux1t4(din, sel, en, dout);
input din;
input en;
input [1:0]sel;
output [3:0]dout;

//net(s)
wire dfeed1; //output of first stage 2:1 DeMux, input for second stage 2:1 Demux
wire dfeed2; //similarly as dfeed1

//logic- structural representation
demux1t2 Dmux1_1(.din(din), .sel(sel[0]), .en(en), .dout0(dfeed1), .dout1(dfeed2));
demux1t2 Dmux2_1(.din(dfeed1), .sel(sel[1]), .en(1'b1), .dout0(dout[0]), .dout1(dout[2]));
demux1t2 Dmux2_2(.din(dfeed2), .sel(sel[1]), .en(1'b1), .dout0(dout[1]), .dout1(dout[3]));

endmodule

//-------------------------------------------------
module demux1t2(din, dout0, dout1, sel, en);
input din;
input sel;
input en;
output dout0;
output dout1;

//net(s)
wire bsel;

//logic- structural representation
not Bsel(bsel, sel); //inverted select signal
and Out_0(dout0, bsel, en, din); //First output data port
and Out_1(dout1, sel, en, din); //Second output data port

endmodule

tb_demux1t4.v
`timescale 1ns / 1ps
//////////////////////////////////////////////////////////////////////////////////
// Company: 
// Engineer: 
// 
// Create Date: 10.04.2026 09:28:01
// Design Name: 
// Module Name: tb_demux1t4
// Project Name: 
// Target Devices: 
// Tool Versions: 
// Description: 
// 
// Dependencies: 
// 
// Revision:
// Revision 0.01 - File Created
// Additional Comments:
// 
//////////////////////////////////////////////////////////////////////////////////


module tb_demux1t4();
reg din;
reg en;
reg [1:0]sel;
wire [3:0]dout;

demux1t4 DeMux(.din(din), .en(en), .sel(sel), .dout(dout));

initial begin //enable signal
#2 en = 0;
#10 en = 1;
end

initial begin //selection and input data 
#5 {din, sel} = 3'bxxx;
#5 {din, sel} = 3'b000;
#5 {din, sel} = 3'b001;
#5 {din, sel} = 3'b010;
#5 {din, sel} = 3'b011;
#5 {din, sel} = 3'b100;
#5 {din, sel} = 3'b101;
#5 {din, sel} = 3'b110;
#5 {din, sel} = 3'b111;
#5 {din, sel} = 3'bx00;
#5 {din, sel} = 3'b1x1;
#5 {din, sel} = 3'b00x;
#5 {din, sel} = 3'b1xx;
end

initial begin //monitor and capture
$monitor("At time: ", $time, ", en: %b, Input: %b, Select: %b, Output line: %b", en, din, sel, dout);
$dumpfile("demux1t4.vcd");
$dumpvars(0, tb_demux1t4);
#100 $finish;
end

endmodule

demux1t4.vcd
$date
   Fri Apr 10 11:24:23 2026
$end

$version
  2025.2
  $dumpfile ("demux1t4.vcd") 
$end

$timescale
  1ps
$end

$scope module tb_demux1t4 $end
$var reg 1 ! din $end
$var reg 1 " en $end
$var reg 2 # sel [1:0] $end
$var wire 4 $ dout [3:0] $end
$scope module DeMux $end
$var wire 1 % din $end
$var wire 1 & en $end
$var wire 2 ' sel [1:0] $end
$var wire 4 $ dout [3:0] $end
$var wire 1 ( dfeed1 $end
$var wire 1 ) dfeed2 $end
$scope module Dmux1_1 $end
$var wire 1 % din $end
$var wire 1 * sel $end
$var wire 1 & en $end
$var wire 1 ( dout0 $end
$var wire 1 ) dout1 $end
$var wire 1 + bsel $end
$upscope $end
$scope module Dmux2_1 $end
$var wire 1 ( din $end
$var wire 1 , sel $end
$var wire 1 - en $end
$var wire 1 . dout0 $end
$var wire 1 / dout1 $end
$var wire 1 0 bsel $end
$upscope $end
$scope module Dmux2_2 $end
$var wire 1 ) din $end
$var wire 1 , sel $end
$var wire 1 1 en $end
$var wire 1 2 dout0 $end
$var wire 1 3 dout1 $end
$var wire 1 4 bsel $end
$upscope $end
$upscope $end
$upscope $end
$enddefinitions $end

#0
$dumpvars
x!
x"
bx #
bx $
x%
x&
bx '
x(
x)
x*
x+
x,
1-
x.
x/
x0
11
x2
x3
x4
$end

#2000
0"
b0 $
0&
0(
0)
0.
0/
02
03

#10000
0!
b0 #
0%
b0 '
0*
1+
0,
10
14

#12000
1"
1&

#15000
b1 #
b1 '
1*
0+
0,

#20000
b10 #
b10 '
0*
1+
1,
00
04

#25000
b11 #
b11 '
1*
0+
1,

#30000
1!
b0 #
b1 $
1%
b0 '
1(
0*
1+
0,
1.
10
14

#35000
b1 #
b10 $
b1 '
0(
1)
1*
0+
0,
0.
12

#40000
b10 #
b100 $
b10 '
1(
0)
0*
1+
1,
1/
00
02
04

#45000
b11 #
b1000 $
b11 '
0(
1)
1*
0+
1,
0/
13

#50000
x!
b0 #
b0x $
x%
b0 '
x(
0)
0*
1+
0,
x.
10
03
14

#55000
1!
bx1 #
bx0x0 $
1%
bx1 '
0(
1)
1*
0+
x,
0.
0/
x0
x2
x3
x4

#60000
0!
b0x #
b0 $
0%
b0x '
0)
x*
x+
0,
10
02
03
14

#65000
1!
bx #
bx $
1%
bx '
x(
x)
x*
x,
x.
x/
x0
x2
x3
x4
